intuno/__init__.py
intuno/__main__.py
intuno/tune.py
intuno-0.1.0.dist-info/LICENSE
intuno-0.1.0.dist-info/METADATA
intuno-0.1.0.dist-info/WHEEL
intuno-0.1.0.dist-info/entry_points.txt
intuno-0.1.0.dist-info/top_level.txt
intuno-0.1.0.dist-info/RECORD
