Metadata-Version: 2.1
Name: intuno
Version: 0.1.0
Summary: Terminal-based note tuning application for pianos and other instruments
Home-page: https://github.com/loukad/intuno
Author: Louka Dlagnekov
Author-email: loukad@gmail.com
License: UNKNOWN
Platform: UNKNOWN
Requires-Python: >=3.7
License-File: LICENSE
Requires-Dist: pyaudio (==0.2.11)
Requires-Dist: numpy (==1.21.2)
Requires-Dist: scipy (==1.7.0)
Requires-Dist: plotille (==3.7.1)
Requires-Dist: blessed (==1.17.10)
